{
  "labId": "Tetratrion-Intro-APIs-Learning-Lab",
  "title": "Tetratrion Introduction APIs Learning Lab",
  "slug": "Introduction to Tetratrion Learning Lab APIs",
  "time": 15,
  "byod": true,
  "files": [
    {"title": "Step 1: Lorem Ipsum Dolor",
     "file":"1.md"},
    {"title": "Step 2: The Next Step Title",
     "file": "2.md"}
  ],
  "tags": [
	{"title": "Tetratrion "}
  ],
  "related": [
  ],
  "authors": [
      {"name": "Krishan Veer", "email": "veer@cisco.com"}
  ],
  "active": true
}
